setup.py
http_client/__init__.py
http_client/base.py
http_client.egg-info/PKG-INFO
http_client.egg-info/SOURCES.txt
http_client.egg-info/dependency_links.txt
http_client.egg-info/requires.txt
http_client.egg-info/top_level.txt